LICENSE
README.md
setup.cfg
setup.py
scienco/__init__.py
scienco/types.py
scienco/utils.py
scienco.egg-info/PKG-INFO
scienco.egg-info/SOURCES.txt
scienco.egg-info/dependency_links.txt
scienco.egg-info/not-zip-safe
scienco.egg-info/top_level.txt
scienco/indexes/__init__.py
scienco/indexes/constants.py
scienco/indexes/processing.py
scienco/metrics/__init__.py
scienco/metrics/constants.py
scienco/metrics/processing.py