Metadata-Version: 2.1
Name: scienco
Version: 0.2.0
Summary: Calculate the readability of text using one of a variety of computed indexes
Home-page: https://gitlab.com/amalchuk/scienco
Author: Andrew Malchuk
Author-email: andrew.malchuk@yandex.ru
License: MIT
Project-URL: Documentation, https://scienco.readable.pw
Project-URL: Source, https://gitlab.com/amalchuk/scienco
Platform: UNKNOWN
Classifier: Development Status :: 5 - Production/Stable
Classifier: Intended Audience :: Education
Classifier: License :: OSI Approved :: MIT License
Classifier: Natural Language :: English
Classifier: Natural Language :: Russian
Classifier: Operating System :: OS Independent
Classifier: Programming Language :: Python
Classifier: Programming Language :: Python :: 3
Classifier: Programming Language :: Python :: 3 :: Only
Classifier: Programming Language :: Python :: 3.6
Classifier: Programming Language :: Python :: 3.7
Classifier: Programming Language :: Python :: 3.8
Classifier: Programming Language :: Python :: 3.9
Classifier: Programming Language :: Python :: Implementation :: CPython
Classifier: Topic :: Text Processing :: Indexing
Classifier: Typing :: Typed
Requires-Python: >=3.6, <4.0
